waldur_site_agent_okd/__init__.py
waldur_site_agent_okd/backend.py
waldur_site_agent_okd/client.py
waldur_site_agent_okd/token_manager.py
waldur_site_agent_okd-0.8.2.dist-info/METADATA
waldur_site_agent_okd-0.8.2.dist-info/WHEEL
waldur_site_agent_okd-0.8.2.dist-info/entry_points.txt
waldur_site_agent_okd-0.8.2.dist-info/RECORD
