Metadata-Version: 2.4
Name: waldur-site-agent-okd
Version: 0.8.2
Summary: OKD/OpenShift plugin for Waldur Site Agent
Author-email: OpenNode Team <info@opennodecloud.com>
Requires-Python: <4,>=3.9
Requires-Dist: kubernetes>=25.0.0
Requires-Dist: requests>=2.31.0
Requires-Dist: waldur-site-agent>=0.7.0
